src/data/Code/A1_first_win.py
src/data/Code/A2_loading_win.py
src/data/Code/A2_photo_win.py
src/data/Code/A3_export_data_win.py
src/data/Code/A4_pdf_win.py
src/data/Code/A5_final_win.py
src/data/Code/Algo_main_CelebA_vf.py
src/data/Code/Main_test.py
src/data/Code/Tuto.py
src/data/Code/image_celeba.py
src/data/IMG/.DS_Store
src/data/IMG/logo_INSA.png
src/data/IMG/resized_logo_INSA.png
src/data/IMG/tuto/.DS_Store
src/data/IMG/tuto/Ima_tuto_1.png
src/data/IMG/tuto/Ima_tuto_2.png
src/data/IMG/tuto/Ima_tuto_3.png
src/data/IMG/tuto/Ima_tuto_4.png
src/data/IMG/tuto/Ima_tuto_5.png
src/data/IMG/tuto/Ima_tuto_6.png
src/data/f_annexes/.DS_Store
src/data/f_annexes/new_list_attr_celba.csv
Codetest1_laguilhon-0.0.54.dist-info/LICENSE
Codetest1_laguilhon-0.0.54.dist-info/METADATA
Codetest1_laguilhon-0.0.54.dist-info/WHEEL
Codetest1_laguilhon-0.0.54.dist-info/top_level.txt
Codetest1_laguilhon-0.0.54.dist-info/RECORD
